ragmint/__init__.py
ragmint/__main__.py
ragmint/app.py
ragmint/autotuner.py
ragmint/explainer.py
ragmint/leaderboard.py
ragmint/qa_generator.py
ragmint/tuner.py
ragmint/core/__init__.py
ragmint/core/chunking.py
ragmint/core/embeddings.py
ragmint/core/evaluation.py
ragmint/core/pipeline.py
ragmint/core/reranker.py
ragmint/core/retriever.py
ragmint/experiments/__init__.py
ragmint/experiments/validation_qa.json
ragmint/integrations/__init__.py
ragmint/integrations/config_adapter.py
ragmint/integrations/langchain_prebuilder.py
ragmint/optimization/__init__.py
ragmint/optimization/search.py
ragmint/tests/__init__.py
ragmint/tests/conftest.py
ragmint/tests/test_autotuner.py
ragmint/tests/test_config_adapter.py
ragmint/tests/test_embeddings.py
ragmint/tests/test_explainer.py
ragmint/tests/test_integration_autotuner_ragmint.py
ragmint/tests/test_langchain_prebuilder.py
ragmint/tests/test_leaderboard.py
ragmint/tests/test_pipeline.py
ragmint/tests/test_qa_generator.py
ragmint/tests/test_retriever.py
ragmint/tests/test_search.py
ragmint/tests/test_tuner.py
ragmint/utils/__init__.py
ragmint/utils/caching.py
ragmint/utils/data_loader.py
ragmint/utils/logger.py
ragmint/utils/metrics.py
ragmint-0.4.9.data/data/LICENSE
ragmint-0.4.9.data/data/README.md
ragmint-0.4.9.dist-info/licenses/LICENSE
ragmint-0.4.9.dist-info/METADATA
ragmint-0.4.9.dist-info/WHEEL
ragmint-0.4.9.dist-info/top_level.txt
ragmint-0.4.9.dist-info/RECORD
