Metadata-Version: 2.4
Name: ragmint
Version: 0.4.9
Summary: A modular framework for evaluating and optimizing RAG pipelines.
Author-email: Andre Oliveira <oandreoliveira@outlook.com>
License: Apache License 2.0
Project-URL: Homepage, https://github.com/andyolivers/ragmint
Project-URL: Documentation, https://andyolivers.com
Project-URL: Issues, https://github.com/andyolivers/ragmint/issues
Keywords: RAG,LLM,retrieval,optimization,AI,evaluation,chunking,autotuning
Requires-Python: >=3.9
License-File: LICENSE
Requires-Dist: numpy<2.0.0
Requires-Dist: pandas>=2.0
Requires-Dist: scikit-learn>=1.3
Requires-Dist: sentence-transformers>=2.2.2
Requires-Dist: chromadb>=0.3.1
Requires-Dist: faiss-cpu; sys_platform != "darwin"
Requires-Dist: faiss-cpu==1.7.4; sys_platform == "darwin"
Requires-Dist: rank-bm25>=0.2.2
Requires-Dist: optuna>=3.0
Requires-Dist: tqdm
Requires-Dist: colorama
Requires-Dist: pyyaml
Requires-Dist: python-dotenv
Requires-Dist: openai>=1.0.0
Requires-Dist: google-generativeai>=0.8.0
Requires-Dist: anthropic>=0.25.0
Requires-Dist: pytest
Requires-Dist: langchain>=0.2.5
Requires-Dist: langchain-community>=0.2.5
Requires-Dist: langchain-text-splitters>=0.2.1
Requires-Dist: gradio>=4.38.0
Requires-Dist: matplotlib>=3.8.0
Requires-Dist: pathspec
Provides-Extra: dev
Requires-Dist: black; extra == "dev"
Requires-Dist: flake8; extra == "dev"
Requires-Dist: isort; extra == "dev"
Requires-Dist: pytest-cov; extra == "dev"
Provides-Extra: docs
Requires-Dist: mkdocs; extra == "docs"
Requires-Dist: mkdocs-material; extra == "docs"
Dynamic: license-file
